gasdiff/__init__.py
gasdiff/__main__.py
gasdiff-0.4.0.dist-info/METADATA
gasdiff-0.4.0.dist-info/WHEEL
gasdiff-0.4.0.dist-info/licenses/LICENSE
gasdiff-0.4.0.dist-info/RECORD
